{"is_source_file": false, "format": "", "description": "", "external_files": [], "external_methods": [], "published": [], "classes": [], "methods": [], "calls": [], "search-terms": ["App.css", "CSS styling", "CSS variables", "media queries", "animation", "responsive design"], "state": 2, "file_id": 8, "knowledge_revision": 27, "git_revision": "7894564180a35a19999e292c8ee71e471016be10", "hash": "eace13d7f1e6345b89bb2bf9871b8196", "format-version": 4, "code-base-name": "pomodoro_timer_frontend", "filename": "pomodoro_timer_frontend/src/App.css", "revision_history": [{"27": "7894564180a35a19999e292c8ee71e471016be10"}]}